[
  {
    "companyName": "阿布",
    "number": 1,
    "link": "www.baidu.com",
    "description": "好公司",
    "alumnus": [
      {
        "name": "koi",
        "phone": "1718",
        "email": "111@163.com"
      }
    ]
  },
  {
    "companyName": "三撒",
    "number": 1,
    "link": "www.baidu.com",
    "description": "好公司",
    "alumnus": [
      {
        "name": "koi",
        "phone": "1718",
        "email": "111@163.com"
      }
    ]
  },
  {
    "companyName": "阿巴",
    "number": 1,
    "link": "www.baidu.com",
    "description": "好公司",
    "alumnus": [
      {
        "name": "koi",
        "phone": "1718",
        "email": "111@163.com"
      }
    ]
  },
  {
    "companyName": "气压",
    "number": 1,
    "link": "www.baidu.com",
    "description": "好公司",
    "alumnus": [
      {
        "name": "koi",
        "phone": "1718",
        "email": "111@163.com"
      },
      {
        "name": "koi",
        "phone": "1718",
        "email": "111@163.com"
      },
      {
        "name": "koi",
        "phone": "1718",
        "email": "111@163.com"
      },
      {
        "name": "koi",
        "phone": "1718",
        "email": "111@163.com"
      },
      {
        "name": "koi",
        "phone": "1718",
        "email": "111@163.com"
      },{
        "name": "koi",
        "phone": "1718",
        "email": "111@163.com"
      }
    ]
  }
]
